NaxieNianWomenYiqiXueXss/README.md
NaxieNianWomenYiqiXueXss/__init__.py
NaxieNianWomenYiqiXueXss/__main__.py
NaxieNianWomenYiqiXueXss/file.epub
NaxieNianWomenYiqiXueXss/index.html
NaxieNianWomenYiqiXueXss/css/__init__.py
NaxieNianWomenYiqiXueXss/css/annotations.css
NaxieNianWomenYiqiXueXss/css/main.css
NaxieNianWomenYiqiXueXss/css/normalize.css
NaxieNianWomenYiqiXueXss/css/popup.css
NaxieNianWomenYiqiXueXss/font/__init__.py
NaxieNianWomenYiqiXueXss/font/fontello.eot
NaxieNianWomenYiqiXueXss/font/fontello.svg
NaxieNianWomenYiqiXueXss/font/fontello.ttf
NaxieNianWomenYiqiXueXss/font/fontello.woff
NaxieNianWomenYiqiXueXss/img/__init__.py
NaxieNianWomenYiqiXueXss/img/annotator-glyph-sprite.png
NaxieNianWomenYiqiXueXss/img/annotator-icon-sprite.png
NaxieNianWomenYiqiXueXss/img/apple-touch-icon.png
NaxieNianWomenYiqiXueXss/img/cancelfullscreen.png
NaxieNianWomenYiqiXueXss/img/close.png
NaxieNianWomenYiqiXueXss/img/fullscreen.png
NaxieNianWomenYiqiXueXss/img/loader.gif
NaxieNianWomenYiqiXueXss/img/menu-icon.png
NaxieNianWomenYiqiXueXss/img/save.png
NaxieNianWomenYiqiXueXss/img/saved.png
NaxieNianWomenYiqiXueXss/img/settings-s.png
NaxieNianWomenYiqiXueXss/img/settings.png
NaxieNianWomenYiqiXueXss/img/star.png
NaxieNianWomenYiqiXueXss/js/__init__.py
NaxieNianWomenYiqiXueXss/js/epub.js
NaxieNianWomenYiqiXueXss/js/epub.min.js
NaxieNianWomenYiqiXueXss/js/epub.min.map
NaxieNianWomenYiqiXueXss/js/hooks.min.js
NaxieNianWomenYiqiXueXss/js/hooks.min.map
NaxieNianWomenYiqiXueXss/js/reader.js
NaxieNianWomenYiqiXueXss/js/reader.js.map
NaxieNianWomenYiqiXueXss/js/reader.min.js
NaxieNianWomenYiqiXueXss/js/reader.min.map
NaxieNianWomenYiqiXueXss/js/hooks/__init__.py
NaxieNianWomenYiqiXueXss/js/hooks/extensions/__init__.py
NaxieNianWomenYiqiXueXss/js/hooks/extensions/highlight.js
NaxieNianWomenYiqiXueXss/js/libs/__init__.py
NaxieNianWomenYiqiXueXss/js/libs/jquery.min.js
NaxieNianWomenYiqiXueXss/js/libs/localforage.min.js
NaxieNianWomenYiqiXueXss/js/libs/screenfull.js
naxie_nian_women_yiqi_xue_xss-2024.3.1.0.dist-info/METADATA
naxie_nian_women_yiqi_xue_xss-2024.3.1.0.dist-info/WHEEL
naxie_nian_women_yiqi_xue_xss-2024.3.1.0.dist-info/entry_points.txt
naxie_nian_women_yiqi_xue_xss-2024.3.1.0.dist-info/top_level.txt
naxie_nian_women_yiqi_xue_xss-2024.3.1.0.dist-info/RECORD
